talk_video_uploader/__init__.py
talk_video_uploader/__main__.py
talk_video_uploader/dumper.py
talk_video_uploader/upload_video.py
talk_video_uploader-0.1.data/data/share/talk-video-uploader/client_id.json
talk_video_uploader-0.1.dist-info/METADATA
talk_video_uploader-0.1.dist-info/RECORD
talk_video_uploader-0.1.dist-info/WHEEL
talk_video_uploader-0.1.dist-info/entry_points.txt
talk_video_uploader-0.1.dist-info/top_level.txt
