Metadata-Version: 2.1
Name: talk-video-uploader
Version: 0.1
Summary: Batch upload talk videos to YouTube
Home-page: https://github.com/oskar456/talk-video-uploader
Author: Ondřej Caletka
Author-email: ondrej@caletka.cz
License: MIT
Platform: UNKNOWN
Classifier: Development Status :: 4 - Beta
Classifier: Intended Audience :: End Users/Desktop
Classifier: Topic :: Multimedia :: Video
Classifier: License :: OSI Approved :: MIT License
Classifier: Programming Language :: Python :: 3
Classifier: Programming Language :: Python :: 3 :: Only
Requires-Python: >=3.6
Requires-Dist: google-api-python-client
Requires-Dist: google-auth-httplib2
Requires-Dist: google-auth-oauthlib
Requires-Dist: pyyaml
Requires-Dist: click
